{
  "_class": "shapeGroup",
  "clippingMaskMode": 0,
  "do_objectID": "E8708C78-71AE-4597-854C-A10E4FCCBB54",
  "exportOptions": {
    "_class": "exportOptions",
    "do_objectID": "7DDC1C2C-9D68-4DB3-9799-1CB64F26E6F9",
    "exportFormats": [
    ],
    "includedLayerIds": [
    ],
    "layerOptions": 0,
    "shouldTrim": false
  },
  "frame": {
    "_class": "rect",
    "constrainProportions": false,
    "do_objectID": "9D1568CA-D43B-44E6-902B-599870FB0FBE",
    "height": 1.035555555555561,
    "width": 9.438202247191043,
    "x": 566.2921348314607,
    "y": 190.5422222222222
  },
  "hasClickThrough": false,
  "hasClippingMask": false,
  "isFlippedHorizontal": false,
  "isFlippedVertical": false,
  "isLocked": false,
  "isVisible": true,
  "layerListExpandedType": 0,
  "layers": [
    {
      "class": "rectangle",
      "id": "9F198208-B296-49D2-83BE-E88DF4DB63EA"
    }
  ],
  "name": "bar_rise",
  "nameIsFixed": false,
  "resizingConstraint": 63,
  "resizingType": 0,
  "rotation": 0,
  "shouldBreakMaskChain": false,
  "style": {
    "_class": "style",
    "borders": [
      {
        "_class": "border",
        "color": {
          "_class": "color",
          "alpha": 1,
          "blue": 0.592,
          "green": 0.592,
          "red": 0.592
        },
        "fillType": 0,
        "isEnabled": false,
        "position": 1,
        "thickness": 1
      }
    ],
    "do_objectID": "329E36F5-30DB-4B67-938E-003EC418E8ED",
    "endDecorationType": 0,
    "fills": [
      {
        "_class": "fill",
        "color": {
          "_class": "color",
          "alpha": 1,
          "blue": 0.3294117647058824,
          "green": 0.3294117647058824,
          "red": 0.9764705882352941
        },
        "fillType": 0,
        "isEnabled": true,
        "noiseIndex": 0,
        "noiseIntensity": 0,
        "patternFillType": 1,
        "patternTileScale": 1
      }
    ],
    "miterLimit": 10,
    "sharedObjectID": "9D5F33C1-E31E-4F0F-8830-0CECFB62EFB7",
    "startDecorationType": 0
  },
  "windingRule": 1
}