{
  "_class": "shapeGroup",
  "clippingMaskMode": 0,
  "do_objectID": "55216A53-C747-4E23-AA39-F256C0DA60C6",
  "exportOptions": {
    "_class": "exportOptions",
    "do_objectID": "042E061B-3343-4721-936B-8184D7EA3F18",
    "exportFormats": [
    ],
    "includedLayerIds": [
    ],
    "layerOptions": 0,
    "shouldTrim": false
  },
  "frame": {
    "_class": "rect",
    "constrainProportions": false,
    "do_objectID": "3536798D-6457-4E50-B3AD-839EB00A3D19",
    "height": 16,
    "width": 16,
    "x": 0,
    "y": 0
  },
  "hasClickThrough": false,
  "hasClippingMask": false,
  "isFlippedHorizontal": true,
  "isFlippedVertical": true,
  "isLocked": true,
  "isVisible": true,
  "layerListExpandedType": 0,
  "layers": [
    {
      "class": "rectangle",
      "id": "92477C89-8B98-4FF8-9B3E-F4CA6FCC4813"
    }
  ],
  "name": "border",
  "nameIsFixed": true,
  "originalObjectID": "9953DED1-726F-4A18-B910-2A9F687B6128",
  "resizingConstraint": 63,
  "resizingType": 0,
  "rotation": 0,
  "shouldBreakMaskChain": false,
  "style": {
    "_class": "style",
    "borders": [
      {
        "_class": "border",
        "color": {
          "_class": "color",
          "alpha": 1,
          "blue": 0.592,
          "green": 0.592,
          "red": 0.592
        },
        "fillType": 0,
        "isEnabled": false,
        "position": 1,
        "thickness": 1
      }
    ],
    "contextSettings": {
      "_class": "graphicsContextSettings",
      "blendMode": 0,
      "do_objectID": "3BB39572-FD09-41D5-9CEA-E49A8E5559C2",
      "opacity": 0
    },
    "do_objectID": "917EC17D-CE92-4202-B9A8-D6C73A429A23",
    "endDecorationType": 0,
    "fills": [
      {
        "_class": "fill",
        "color": {
          "_class": "color",
          "alpha": 1,
          "blue": 0.847,
          "green": 0.847,
          "red": 0.847
        },
        "fillType": 0,
        "isEnabled": true,
        "noiseIndex": 0,
        "noiseIntensity": 0,
        "patternFillType": 1,
        "patternTileScale": 1
      }
    ],
    "miterLimit": 10,
    "startDecorationType": 0
  },
  "windingRule": 1
}