{
  "_class": "shapeGroup",
  "clippingMaskMode": 0,
  "do_objectID": "E5C7D67E-478C-4E11-9969-D0603F6715BC",
  "exportOptions": {
    "_class": "exportOptions",
    "do_objectID": "66DC66B8-EC34-463F-9F90-07CA56911D3A",
    "exportFormats": [
    ],
    "includedLayerIds": [
    ],
    "layerOptions": 0,
    "shouldTrim": false
  },
  "frame": {
    "_class": "rect",
    "constrainProportions": true,
    "do_objectID": "1E51D5EC-421A-4577-80C2-2E66B6BE4D7E",
    "height": 12,
    "width": 10,
    "x": 8,
    "y": 6
  },
  "hasClickThrough": false,
  "hasClippingMask": false,
  "isFlippedHorizontal": false,
  "isFlippedVertical": false,
  "isLocked": false,
  "isVisible": true,
  "layerListExpandedType": 0,
  "layers": [
    {
      "class": "shapePath",
      "id": "5097CDBD-C94D-4279-B820-F06A63B298B2"
    }
  ],
  "name": "Shape",
  "nameIsFixed": false,
  "resizingConstraint": 63,
  "resizingType": 0,
  "rotation": 0,
  "shouldBreakMaskChain": false,
  "style": {
    "_class": "style",
    "do_objectID": "68332954-7D54-47FC-A52A-17ECE34263F9",
    "endDecorationType": 0,
    "fills": [
      {
        "_class": "fill",
        "color": {
          "_class": "color",
          "alpha": 1,
          "blue": 1,
          "green": 1,
          "red": 1
        },
        "fillType": 0,
        "isEnabled": true,
        "noiseIndex": 0,
        "noiseIntensity": 0,
        "patternFillType": 1,
        "patternTileScale": 1
      }
    ],
    "miterLimit": 10,
    "startDecorationType": 0
  },
  "windingRule": 0
}