{
  "_class": "shapeGroup",
  "clippingMaskMode": 0,
  "do_objectID": "FD739FCA-ABCF-4A09-A639-B9CD82591EE7",
  "exportOptions": {
    "_class": "exportOptions",
    "do_objectID": "FB763D55-BE46-4F4C-AB5A-9018FC186DAC",
    "exportFormats": [
    ],
    "includedLayerIds": [
    ],
    "layerOptions": 0,
    "shouldTrim": false
  },
  "frame": {
    "_class": "rect",
    "constrainProportions": false,
    "do_objectID": "11315DEC-F063-4947-A91B-7F13BDE3BDD5",
    "height": 6.629066666666667,
    "width": 4.542800000000001,
    "x": 4.3496,
    "y": 0.6854666666666664
  },
  "hasClickThrough": false,
  "hasClippingMask": false,
  "isFlippedHorizontal": false,
  "isFlippedVertical": false,
  "isLocked": false,
  "isVisible": true,
  "layerListExpandedType": 0,
  "layers": [
    {
      "class": "shapePath",
      "id": "F8CB89A1-ECBE-4BD4-AB5A-FA33E213BC26"
    }
  ],
  "name": "Shape",
  "nameIsFixed": false,
  "resizingConstraint": 63,
  "resizingType": 0,
  "rotation": 0,
  "shouldBreakMaskChain": false,
  "style": {
    "_class": "style",
    "do_objectID": "EC4BD900-6C3F-4A3F-8DAA-FCADC7F25784",
    "endDecorationType": 0,
    "fills": [
      {
        "_class": "fill",
        "color": {
          "_class": "color",
          "alpha": 1,
          "blue": 0.211764705882353,
          "green": 0.2627450980392158,
          "red": 0.9568627450980393
        },
        "fillType": 0,
        "isEnabled": true,
        "noiseIndex": 0,
        "noiseIntensity": 0,
        "patternFillType": 1,
        "patternTileScale": 1
      }
    ],
    "miterLimit": 10,
    "startDecorationType": 0
  },
  "windingRule": 1
}