{
  "_class": "symbolInstance",
  "do_objectID": "D6618D40-5C18-4D63-92F5-255C57DF4C3F",
  "exportOptions": {
    "_class": "exportOptions",
    "do_objectID": "F22CC41C-CD36-4C3A-8398-1CBACEFAF7F1",
    "exportFormats": [
    ],
    "includedLayerIds": [
    ],
    "layerOptions": 0,
    "shouldTrim": false
  },
  "frame": {
    "_class": "rect",
    "constrainProportions": false,
    "do_objectID": "DABBDCC3-589B-49D2-9382-054CEEA9EC28",
    "height": 32,
    "width": 490,
    "x": 289,
    "y": 692
  },
  "horizontalSpacing": 0,
  "isFlippedHorizontal": false,
  "isFlippedVertical": false,
  "isLocked": false,
  "isVisible": true,
  "layerListExpandedType": 0,
  "name": "elements/chart settings/flat 2 active",
  "nameIsFixed": false,
  "overrideValues": [
  ],
  "overrides": {
  },
  "resizingConstraint": 63,
  "resizingType": 0,
  "rotation": 0,
  "scale": 1,
  "shouldBreakMaskChain": false,
  "style": {
    "_class": "style",
    "do_objectID": "A29AD86A-8C59-4785-9288-C7FE44B81629",
    "endDecorationType": 0,
    "miterLimit": 10,
    "shadows": [
      {
        "_class": "shadow",
        "blurRadius": 6,
        "color": {
          "_class": "color",
          "alpha": 0.14,
          "blue": 0.6078431372549019,
          "green": 0.2039215686274509,
          "red": 0.1333333333333333
        },
        "contextSettings": {
          "_class": "graphicsContextSettings",
          "blendMode": 0,
          "opacity": 1
        },
        "isEnabled": true,
        "offsetX": 0,
        "offsetY": 1,
        "spread": 0
      }
    ],
    "startDecorationType": 0
  },
  "symbolID": "B243581E-38FD-490D-B7C4-C29D42DDA284",
  "verticalSpacing": 0
}