{
  "_class": "shapeGroup",
  "clippingMaskMode": 0,
  "do_objectID": "65A921DF-96FF-4E21-A994-70C8ABB8351C",
  "exportOptions": {
    "_class": "exportOptions",
    "do_objectID": "06946DA2-56CA-4F1C-8203-632068400FB6",
    "exportFormats": [
    ],
    "includedLayerIds": [
    ],
    "layerOptions": 0,
    "shouldTrim": false
  },
  "frame": {
    "_class": "rect",
    "constrainProportions": false,
    "do_objectID": "E74F2305-A168-4D72-8241-8903E50DF6BC",
    "height": 48,
    "width": 48,
    "x": 0,
    "y": 0
  },
  "hasClickThrough": false,
  "hasClippingMask": false,
  "isFlippedHorizontal": true,
  "isFlippedVertical": true,
  "isLocked": true,
  "isVisible": true,
  "layerListExpandedType": 0,
  "layers": [
    {
      "class": "rectangle",
      "id": "E13D0AD0-C131-4C9F-84FF-58DFF22DE790"
    }
  ],
  "name": "border",
  "nameIsFixed": true,
  "originalObjectID": "2A606D6C-8506-4625-A515-04D27D5E2F3F",
  "resizingConstraint": 63,
  "resizingType": 0,
  "rotation": 0,
  "shouldBreakMaskChain": false,
  "style": {
    "_class": "style",
    "borders": [
      {
        "_class": "border",
        "color": {
          "_class": "color",
          "alpha": 1,
          "blue": 0.592,
          "green": 0.592,
          "red": 0.592
        },
        "fillType": 0,
        "isEnabled": false,
        "position": 1,
        "thickness": 1
      }
    ],
    "contextSettings": {
      "_class": "graphicsContextSettings",
      "blendMode": 0,
      "do_objectID": "D0E99708-8899-47A2-8E10-B60FB33BB68A",
      "opacity": 0
    },
    "do_objectID": "0285BF91-13B7-40A5-B977-73C0D6A58CA4",
    "endDecorationType": 0,
    "fills": [
      {
        "_class": "fill",
        "color": {
          "_class": "color",
          "alpha": 1,
          "blue": 0.3215686274509804,
          "green": 0.1882352941176471,
          "red": 0.1647058823529412
        },
        "fillType": 0,
        "isEnabled": true,
        "noiseIndex": 0,
        "noiseIntensity": 0,
        "patternFillType": 1,
        "patternTileScale": 1
      }
    ],
    "miterLimit": 10,
    "startDecorationType": 0
  },
  "windingRule": 1
}