{
  "_class": "shapeGroup",
  "clippingMaskMode": 0,
  "do_objectID": "E8F5053E-89C3-4F83-841B-75495AFD9581",
  "exportOptions": {
    "_class": "exportOptions",
    "do_objectID": "F7EBA59A-04FA-414A-8E32-26614A98F753",
    "exportFormats": [
    ],
    "includedLayerIds": [
    ],
    "layerOptions": 0,
    "shouldTrim": false
  },
  "frame": {
    "_class": "rect",
    "constrainProportions": true,
    "do_objectID": "480F9B6F-E1CD-40E4-9605-352C1652E57B",
    "height": 4,
    "width": 4,
    "x": 6,
    "y": 6
  },
  "hasClickThrough": false,
  "hasClippingMask": false,
  "isFlippedHorizontal": false,
  "isFlippedVertical": false,
  "isLocked": false,
  "isVisible": true,
  "layerListExpandedType": 0,
  "layers": [
    {
      "class": "oval",
      "id": "FB65F6C0-7947-4A5E-9492-AB2E91B721C1"
    }
  ],
  "name": "Oval Copy",
  "nameIsFixed": false,
  "originalObjectID": "506A5A81-B73F-4B7D-B828-2B0571162368",
  "resizingConstraint": 63,
  "resizingType": 0,
  "rotation": 0,
  "shouldBreakMaskChain": false,
  "style": {
    "_class": "style",
    "borders": [
      {
        "_class": "border",
        "color": {
          "_class": "color",
          "alpha": 1,
          "blue": 0.592,
          "green": 0.592,
          "red": 0.592
        },
        "fillType": 0,
        "isEnabled": false,
        "position": 1,
        "thickness": 1
      }
    ],
    "do_objectID": "1CB22877-E8CE-47FF-9D81-CF78AD76401C",
    "endDecorationType": 0,
    "fills": [
      {
        "_class": "fill",
        "color": {
          "_class": "color",
          "alpha": 1,
          "blue": 0.3215686274509804,
          "green": 0.188235294117647,
          "red": 0.1647058823529412
        },
        "fillType": 0,
        "isEnabled": true,
        "noiseIndex": 0,
        "noiseIntensity": 0,
        "patternFillType": 1,
        "patternTileScale": 1
      }
    ],
    "miterLimit": 10,
    "startDecorationType": 0
  },
  "windingRule": 1
}