{
  "_class": "shapeGroup",
  "clippingMaskMode": 0,
  "do_objectID": "06571F5F-1616-46AE-8912-DD92B60C5BD0",
  "exportOptions": {
    "_class": "exportOptions",
    "do_objectID": "9A50EA25-1C0D-4D3C-AF72-2A22683280A3",
    "exportFormats": [
    ],
    "includedLayerIds": [
    ],
    "layerOptions": 0,
    "shouldTrim": false
  },
  "frame": {
    "_class": "rect",
    "constrainProportions": false,
    "do_objectID": "AFC31F2D-D011-4778-BD19-773F105D8E35",
    "height": 341.2499999998106,
    "width": 828,
    "x": 0,
    "y": 241
  },
  "hasClickThrough": false,
  "hasClippingMask": false,
  "isFlippedHorizontal": false,
  "isFlippedVertical": false,
  "isLocked": false,
  "isVisible": true,
  "layerListExpandedType": 0,
  "layers": [
    {
      "class": "shapePath",
      "id": "7889C234-2DBD-4D8B-A6D0-C3744C4A1534"
    }
  ],
  "name": "Shape",
  "nameIsFixed": false,
  "resizingConstraint": 63,
  "resizingType": 0,
  "rotation": 0,
  "shouldBreakMaskChain": false,
  "style": {
    "_class": "style",
    "borderOptions": {
      "_class": "borderOptions",
      "dashPattern": [
      ],
      "do_objectID": "B5F6DE45-6E32-48EE-B1B9-2A8DB3393354",
      "isEnabled": false,
      "lineCapStyle": 1,
      "lineJoinStyle": 1
    },
    "borders": [
      {
        "_class": "border",
        "color": {
          "_class": "color",
          "alpha": 1,
          "blue": 0.5294117647058821,
          "green": 0.8117647058823529,
          "red": 0.2549019607843137
        },
        "fillType": 0,
        "isEnabled": true,
        "position": 0,
        "thickness": 2
      }
    ],
    "do_objectID": "21F04E74-E41A-4416-AAE6-0DF9E8E4E99A",
    "endDecorationType": 0,
    "miterLimit": 10,
    "startDecorationType": 0
  },
  "windingRule": 1
}