{
  "_class": "shapeGroup",
  "clippingMaskMode": 0,
  "do_objectID": "71856F8D-FF4E-44B7-9C45-3DBC193EFC95",
  "exportOptions": {
    "_class": "exportOptions",
    "do_objectID": "A56F09FB-8BF9-4457-8792-82388E518ADB",
    "exportFormats": [
    ],
    "includedLayerIds": [
    ],
    "layerOptions": 0,
    "shouldTrim": false
  },
  "frame": {
    "_class": "rect",
    "constrainProportions": false,
    "do_objectID": "F894A988-76E4-4C32-A996-43A6E396DAC4",
    "height": 1,
    "width": 5.99977903169656,
    "x": 0,
    "y": 1.5
  },
  "hasClickThrough": false,
  "hasClippingMask": false,
  "isFlippedHorizontal": false,
  "isFlippedVertical": false,
  "isLocked": false,
  "isVisible": true,
  "layerListExpandedType": 0,
  "layers": [
    {
      "class": "shapePath",
      "id": "4A8E5237-DDD1-4449-9FF9-FAF6B43AF066"
    }
  ],
  "name": "Path 2",
  "nameIsFixed": false,
  "originalObjectID": "303A876D-EB2C-47CF-9BBD-96A292501B3D",
  "resizingConstraint": 63,
  "resizingType": 0,
  "rotation": 0,
  "shouldBreakMaskChain": false,
  "style": {
    "_class": "style",
    "do_objectID": "23F0C458-392B-415D-A5A1-E48BC6C628D4",
    "endDecorationType": 0,
    "fills": [
      {
        "_class": "fill",
        "color": {
          "_class": "color",
          "alpha": 1,
          "blue": 1,
          "green": 1,
          "red": 1
        },
        "fillType": 0,
        "isEnabled": true,
        "noiseIndex": 0,
        "noiseIntensity": 0,
        "patternFillType": 1,
        "patternTileScale": 1
      }
    ],
    "miterLimit": 10,
    "startDecorationType": 0
  },
  "windingRule": 0
}