{
  "_class": "symbolInstance",
  "do_objectID": "7D87EAEC-3A0F-4D1A-A559-197FC4837E07",
  "exportOptions": {
    "_class": "exportOptions",
    "do_objectID": "542504C4-CDCF-4405-B07E-80E76D5209A6",
    "exportFormats": [
    ],
    "includedLayerIds": [
    ],
    "layerOptions": 0,
    "shouldTrim": false
  },
  "frame": {
    "_class": "rect",
    "constrainProportions": false,
    "do_objectID": "C95511EA-037F-48DD-918C-CFC9FFC2AF4B",
    "height": 16,
    "width": 16,
    "x": 300,
    "y": 8
  },
  "horizontalSpacing": 0,
  "isFlippedHorizontal": false,
  "isFlippedVertical": false,
  "isLocked": false,
  "isVisible": true,
  "layerListExpandedType": 0,
  "name": "Question/Dark",
  "nameIsFixed": false,
  "originalObjectID": "38285DD6-48DE-449A-B8A0-237B6858D15F",
  "overrideValues": [
  ],
  "overrides": {
  },
  "resizingConstraint": 63,
  "resizingType": 0,
  "rotation": 0,
  "scale": 1,
  "shouldBreakMaskChain": false,
  "style": {
    "_class": "style",
    "do_objectID": "15592896-2F10-4841-84BD-BAB5F5960D35",
    "endDecorationType": 0,
    "miterLimit": 10,
    "startDecorationType": 0
  },
  "symbolID": "3E140B94-9566-4CD2-BD2D-B7107BCC9257",
  "verticalSpacing": 0
}