{
  "_class": "group",
  "do_objectID": "7FDAC26B-3658-43B6-855B-79E4BD28E0CA",
  "exportOptions": {
    "_class": "exportOptions",
    "do_objectID": "1CF5931E-85E0-4B48-AD79-6D19EA3498C2",
    "exportFormats": [
    ],
    "includedLayerIds": [
    ],
    "layerOptions": 0,
    "shouldTrim": false
  },
  "frame": {
    "_class": "rect",
    "constrainProportions": false,
    "do_objectID": "0411BDE7-271B-4C86-B47D-8219A314BFD3",
    "height": 200,
    "width": 300,
    "x": 10,
    "y": 332
  },
  "hasClickThrough": false,
  "isFlippedHorizontal": false,
  "isFlippedVertical": false,
  "isLocked": false,
  "isVisible": true,
  "layerListExpandedType": 0,
  "layers": [
    {
      "class": "shapeGroup",
      "id": "8A59F0FA-5CC6-45F3-9915-708C1947CD0D"
    },
    {
      "class": "text",
      "id": "13FD41A1-08AA-42D1-BA5D-DE1705F5AC00"
    },
    {
      "class": "group",
      "id": "9357782E-69AA-4D10-BD9A-11F871A91923"
    }
  ],
  "name": "list",
  "nameIsFixed": true,
  "resizingConstraint": 63,
  "resizingType": 0,
  "rotation": 0,
  "shouldBreakMaskChain": false,
  "style": {
    "_class": "style",
    "do_objectID": "2330C2B0-512B-414B-9E53-DCA540383A42",
    "endDecorationType": 0,
    "miterLimit": 10,
    "shadows": [
      {
        "_class": "shadow",
        "blurRadius": 8,
        "color": {
          "_class": "color",
          "alpha": 0.14,
          "blue": 0.3215686274509804,
          "green": 0.188235294117647,
          "red": 0.1647058823529412
        },
        "contextSettings": {
          "_class": "graphicsContextSettings",
          "blendMode": 0,
          "opacity": 1
        },
        "isEnabled": true,
        "offsetX": 0,
        "offsetY": 2,
        "spread": 0
      }
    ],
    "startDecorationType": 0
  }
}